mous3/__init__.py
mous3/__main__.py
mous3-0.1.2.dist-info/LICENSE
mous3-0.1.2.dist-info/METADATA
mous3-0.1.2.dist-info/WHEEL
mous3-0.1.2.dist-info/entry_points.txt
mous3-0.1.2.dist-info/top_level.txt
mous3-0.1.2.dist-info/RECORD
