Metadata-Version: 2.1
Name: mous3
Version: 0.1.2
Summary: Allows head or tail of a file on s3 without downloading the whole file
Author-email: Spencer Smith <spencer@auriasllc.com>
License: This is free and unencumbered software released into the public domain.
Project-URL: Homepage, https://github.com/spencersmith/mous3
Keywords: aws,s3,head,tail
Classifier: License :: OSI Approved :: The Unlicense (Unlicense)
Classifier: Operating System :: OS Independent
Classifier: Programming Language :: Python :: 3
Requires-Python: >=3.6
License-File: LICENSE
Requires-Dist: boto3
